myproj/__init__.py
myproj/module.py
complex_package-0.0.1.dist-info/LICENSE
complex_package-0.0.1.dist-info/METADATA
complex_package-0.0.1.dist-info/WHEEL
complex_package-0.0.1.dist-info/top_level.txt
complex_package-0.0.1.dist-info/RECORD
