Metadata-Version: 2.1
Name: complex-package
Version: 0.0.1
Summary: A class for using complex numbers
Home-page: https://github.com/pypa/sampleproject
Author: LR
Author-email: author@example.com
License: UNKNOWN
Platform: UNKNOWN
Classifier: Programming Language :: Python :: 3
Classifier: License :: OSI Approved :: MIT License
Classifier: Operating System :: OS Independent
